fast_alignment/__init__.py
fast_alignment/_version.py
fast_alignment/basenet.py
fast_alignment/predictor.py
fast_alignment/utils.py
fast_alignment-0.0.1.dist-info/METADATA
fast_alignment-0.0.1.dist-info/WHEEL
fast_alignment-0.0.1.dist-info/top_level.txt
fast_alignment-0.0.1.dist-info/RECORD
